zaber/__init__.py
zaber/serial/__init__.py
zaber/serial/asciiaxis.py
zaber/serial/asciicommand.py
zaber/serial/asciidevice.py
zaber/serial/asciilockstep.py
zaber/serial/asciilockstepinfo.py
zaber/serial/asciimovementmixin.py
zaber/serial/asciireply.py
zaber/serial/asciiserial.py
zaber/serial/binarycommand.py
zaber/serial/binarydevice.py
zaber/serial/binaryreply.py
zaber/serial/binaryserial.py
zaber/serial/portlock.py
zaber/serial/timeouterror.py
zaber/serial/unexpectedreplyerror.py
zaber/serial/utils.py
zaber.serial-0.9.1.dist-info/LICENSE.txt
zaber.serial-0.9.1.dist-info/METADATA
zaber.serial-0.9.1.dist-info/WHEEL
zaber.serial-0.9.1.dist-info/top_level.txt
zaber.serial-0.9.1.dist-info/RECORD
