Metadata-Version: 2.1
Name: zaber.serial
Version: 0.9.1
Summary: A library for communicating with Zaber devices
Home-page: http://www.zaber.com/support/docs/api/core-python/
Author: Zaber Technologies Inc.
Author-email: contact@zaber.com
License: Apache Software License v2.0
Keywords: serial zaber
Platform: UNKNOWN
Classifier: Development Status :: 2 - Pre-Alpha
Classifier: Intended Audience :: Developers
Classifier: License :: OSI Approved :: Apache Software License
Classifier: Topic :: Software Development :: Libraries
Classifier: Programming Language :: Python :: 2
Classifier: Programming Language :: Python :: 2.7
Classifier: Programming Language :: Python :: 3
Classifier: Programming Language :: Python :: 3.5
Requires-Dist: pyserial
Provides-Extra: test
Requires-Dist: pytest ; extra == 'test'
